Metadata-Version: 2.1
Name: DataPrepKitz
Version: 0.1.0
Summary: A package for data preprocessing tasks
Home-page: https://github.com/zuhair31002/DataPrepKitz
Author: zuhairalorfahly
Author-email: zuhairalorfahly@gmail.com
Classifier: Programming Language :: Python :: 3
Classifier: License :: OSI Approved :: MIT License
Classifier: Operating System :: OS Independent
Requires-Python: >=3.6
License-File: LICENSE
Requires-Dist: pandas
Requires-Dist: numpy
Requires-Dist: scikit-learn
